onepasswd/__init__.py
onepasswd/client.py
onepasswd/config.py
onepasswd/crypto.py
onepasswd/ltlog.py
onepasswd/onepasswd.py
onepasswd/web.py
onepasswd/templates/index.html
onepasswd/templates/static/bootstrap.bundle.min.js
onepasswd/templates/static/bootstrap.min.css
onepasswd/templates/static/inconsolata:wght@500.css
onepasswd/templates/static/jquery-3.6.4.min.js
onepasswd/templates/static/jsencrypt.min.js
onepasswd/tools/__init__.py
onepasswd/tools/jdiff.py
onepasswd/tools/jmerge.py
onepasswd/tools/upgrade.py
onepasswd-0.2.6.dist-info/METADATA
onepasswd-0.2.6.dist-info/WHEEL
onepasswd-0.2.6.dist-info/entry_points.txt
onepasswd-0.2.6.dist-info/top_level.txt
onepasswd-0.2.6.dist-info/RECORD
