Metadata-Version: 2.1
Name: onepasswd
Version: 0.2.6
Summary: onepasswd
Home-page: https://github.com/agfn/onepasswd
Author: agfn
Author-email: lavender.tree9988@gmail.com
Project-URL: Bug Tracker, https://github.com/agfn/onepasswd/issues
Classifier: Programming Language :: Python :: 3
Classifier: License :: OSI Approved :: MIT License
Classifier: Operating System :: OS Independent
Requires-Python: >=3.6
Requires-Dist: setuptools-scm
Requires-Dist: pycryptodome
Requires-Dist: pyperclip
Requires-Dist: requests
Requires-Dist: colored
Requires-Dist: click
Requires-Dist: PyGithub
